serpentime/__init__.py
serpentime/app.py
serpentime/core/__init__.py
serpentime/core/chronodex.py
serpentime/core/tests/__init__.py
serpentime/core/tests/test_chronodex.py
serpentime/files/__init__.py
serpentime/files/preferences.json
serpentime/files/data/20191119.csv
serpentime/files/data/20191119.txt
serpentime/files/data/20191120.csv
serpentime/files/data/20191120.txt
serpentime/files/data/20210212.csv
serpentime/files/data/20210212.txt
serpentime/files/data/20210213.csv
serpentime/files/data/20210218.csv
serpentime/files/data/20210219.csv
serpentime/files/data/20210220.csv
serpentime/files/data/20210221.csv
serpentime/files/data/__init__.py
serpentime/ui/__init__.py
serpentime/ui/app_model.py
serpentime/ui/app_view.py
serpentime/ui/chronodex_graph.py
serpentime/ui/chronodex_table_model.py
serpentime/ui/item_delegates.py
serpentime/ui/pref_table_model.py
serpentime/ui/icons/add-black-18dp.svg
serpentime/ui/icons/delete-black-18dp.svg
serpentime/ui/icons/download-black-18dp.svg
serpentime/ui/icons/remove-black-18dp.svg
serpentime/ui/icons/save-black-18dp.svg
serpentime/ui/tests/__init__.py
serpentime/ui/tests/test_app_view.py
serpentime-0.0.2.dist-info/LICENSE
serpentime-0.0.2.dist-info/METADATA
serpentime-0.0.2.dist-info/WHEEL
serpentime-0.0.2.dist-info/top_level.txt
serpentime-0.0.2.dist-info/RECORD
