Metadata-Version: 2.1
Name: serpentime
Version: 0.0.2
Summary: A Chronodex like time management tool
Home-page: https://github.com/xamcost/serpentime
Author: Maxime Costalonga
License: UNKNOWN
Platform: UNKNOWN
Requires-Dist: requests
Requires-Dist: pyqt5
Requires-Dist: importlib ; python_version == "2.6"
